escape_abm/__init__.py
escape_abm/alias_table.py
escape_abm/ast.py
escape_abm/check_ast.py
escape_abm/cli.py
escape_abm/click_helpers.py
escape_abm/codegen_openmp.py
escape_abm/input_helpers.py
escape_abm/language_server.py
escape_abm/misc.py
escape_abm/output_helpers.py
escape_abm/parse_tree.py
escape_abm/tree_sitter_bindings.py
escape_abm/utils.py
escape_abm/static/simulation_common_openmp.h
escape_abm/templates/apply_statement_defn_openmp.jinja2
escape_abm/templates/apply_statement_launch_openmp.jinja2
escape_abm/templates/call_statement.jinja2
escape_abm/templates/cmakelists_txt_openmp.jinja2
escape_abm/templates/contagion_methods.jinja2
escape_abm/templates/discrete_dist_defn.jinja2
escape_abm/templates/edge_table_defn.jinja2
escape_abm/templates/enum_defn.jinja2
escape_abm/templates/function_decl.jinja2
escape_abm/templates/function_defn.jinja2
escape_abm/templates/global_defn.jinja2
escape_abm/templates/if_statement.jinja2
escape_abm/templates/node_table_defn.jinja2
escape_abm/templates/normal_dist_defn.jinja2
escape_abm/templates/pass_statement.jinja2
escape_abm/templates/print_statement.jinja2
escape_abm/templates/reduce_statement_defn_openmp.jinja2
escape_abm/templates/reduce_statement_launch_openmp.jinja2
escape_abm/templates/return_statement.jinja2
escape_abm/templates/sample_statement_launch_openmp.jinja2
escape_abm/templates/select_statement_defn_openmp.jinja2
escape_abm/templates/select_statement_launch_openmp.jinja2
escape_abm/templates/simulator_openmp.jinja2
escape_abm/templates/switch_statement.jinja2
escape_abm/templates/uniform_dist_defn.jinja2
escape_abm/templates/update_statement.jinja2
escape_abm/templates/variable.jinja2
escape_abm/templates/while_loop.jinja2
escape_abm-0.0.1.dist-info/LICENSE
escape_abm-0.0.1.dist-info/METADATA
escape_abm-0.0.1.dist-info/WHEEL
escape_abm-0.0.1.dist-info/entry_points.txt
escape_abm-0.0.1.dist-info/top_level.txt
escape_abm-0.0.1.dist-info/RECORD
