Metadata-Version: 2.1
Name: escape-abm
Version: 0.0.1
Summary: Epidemic Simulator Compiler and Programming Environment
Author-email: Parantapa Bhattacharya <parantapa@virginia.edu>
Project-URL: Homepage, http://github.com/nssac/escape-abm
Classifier: Programming Language :: Python :: 3
Classifier: License :: OSI Approved :: MIT License
Classifier: Operating System :: OS Independent
Requires-Python: >=3.11
License-File: LICENSE
Requires-Dist: click
Requires-Dist: platformdirs
Requires-Dist: rich
Requires-Dist: tree-sitter
Requires-Dist: tree-sitter-esl
Requires-Dist: jinja2
Requires-Dist: pygls
Requires-Dist: numpy
Requires-Dist: scipy
Requires-Dist: pandas
Requires-Dist: pyarrow
Requires-Dist: polars
Requires-Dist: h5py
Requires-Dist: typeguard
Requires-Dist: pydantic
